mccmnc/__init__.py
mccmnc/cli.py
mccmnc/mccmnc.py
mccmnc-3.3.dist-info/LICENSE
mccmnc-3.3.dist-info/METADATA
mccmnc-3.3.dist-info/WHEEL
mccmnc-3.3.dist-info/entry_points.txt
mccmnc-3.3.dist-info/top_level.txt
mccmnc-3.3.dist-info/RECORD
