Metadata-Version: 2.1
Name: mccmnc
Version: 3.3
Summary: A tool for matching and retrieving information about MCC-MNC combinations.
Home-page: https://github.com/jbjulia/mcc-mnc
Author: Joseph Julian
Author-email: jbjulian@pm.me
Classifier: Programming Language :: Python :: 3
Classifier: License :: OSI Approved :: MIT License
Classifier: Operating System :: OS Independent
Requires-Python: >=3.6
License-File: LICENSE
Requires-Dist: beautifulsoup4
Requires-Dist: tqdm
